Metadata-Version: 2.1
Name: Wddspider
Version: 0.0.1
Summary: Loveyou
Home-page: UNKNOWN
Author: wangdengdeng
Author-email: jimmybutler19@163.com
Maintainer: me
Maintainer-email: jimmybutler19@163.com
License: MIT License
Platform: UNKNOWN
Classifier: Development Status :: 3 - Alpha
Classifier: Intended Audience :: Developers
Classifier: Topic :: Software Development :: Build Tools
Classifier: License :: OSI Approved :: MIT License
Classifier: Programming Language :: Python :: 3
Requires-Python: >=3.9
